coworker/__init__.py
coworker-2.0.1.dist-info/LICENSE
coworker-2.0.1.dist-info/METADATA
coworker-2.0.1.dist-info/WHEEL
coworker-2.0.1.dist-info/top_level.txt
coworker-2.0.1.dist-info/RECORD
