Metadata-Version: 2.1
Name: coworker
Version: 2.0.1
Summary: Generic worker that performs concurrent tasks using coroutine.
Home-page: https://github.com/maxzheng/coworker
Author: Max Zheng
Author-email: maxzheng.os @t gmail.com
License: MIT
Keywords: coroutine concurrent worker
Classifier: Development Status :: 5 - Production/Stable
Classifier: Intended Audience :: Developers
Classifier: Topic :: Software Development :: Libraries :: Python Modules
Classifier: License :: OSI Approved :: MIT License
Classifier: Programming Language :: Python :: 3.5
License-File: LICENSE
